pyguidesktop/__init__.py
pyguidesktop/guidesktop.py
pyguidesktop/logger.py
pyguidesktop/pyguidesktop.py
pyguidesktop/tests.py
pyguidesktop-0.3.dist-info/LICENSE
pyguidesktop-0.3.dist-info/METADATA
pyguidesktop-0.3.dist-info/WHEEL
pyguidesktop-0.3.dist-info/top_level.txt
pyguidesktop-0.3.dist-info/RECORD
